{
  "type": "create:compacting",
  "ingredients": [
    {
      "tag": "forge:nuggets/iron"
    },
    {
      "tag": "forge:nuggets/iron"
    },
    {
      "tag": "forge:nuggets/iron"
    },
    {
      "tag": "forge:nuggets/iron"
    },
    {
      "tag": "forge:nuggets/iron"
    },
    {
      "tag": "forge:nuggets/iron"
    },
    {
      "tag": "forge:nuggets/iron"
    },
    {
      "tag": "forge:nuggets/iron"
    },
    {
      "tag": "forge:nuggets/iron"
    }
  ],
  "results": [
    {
      "item": "minecraft:iron_ingot"
    }
  ],
  "heatRequirement": "heated"
}